{
  "symbol": "BMNR",
  "companyName": "Bitmine Immersion Technologies, Inc.",
  "analysisDate": "2026-03-29",
  "currentPrice": 18.39,
  "marketCap": "$8.6B",
  "businessSummary": {
    "oneLiner": "세계 최대 상장 Ethereum 보유 기업, MicroStrategy의 Bitcoin 전략을 Ethereum에 적용한 디지털 자산 트레저리 회사",
    "description": "원래 Bitcoin 채굴 회사였으나 Tom Lee(Fundstrat 공동 창업자) 합류 후 Ethereum 트레저리 전략으로 피봇. 3/22 기준 4,660,903 ETH(총 공급량의 3.86%) 보유, 총 크립토+현금 $10.9B. MAVAN 스테이킹 플랫폼 론칭으로 연 $300M+ 매출 목표. ETH가 $2,000 근처에서 아슬아슬하게 버티는 중이다.",
    "howTheyMakeMoney": [
      "ETH 트레저리: 4,660,903 ETH 보유 (~$9.4B at ~$2,000/ETH)",
      "ETH 스테이킹 수익: 3,142,643 ETH 스테이킹, MAVAN 이관 후 연간 ~$300M 목표",
      "배당: 5.1% 배당수익률, 크립토 트레저리 기업 중 유일",
      "비트코인 보유: 196 BTC 보유 (부수적)"
    ],
    "keyProducts": ["Ethereum Treasury", "MAVAN (Made in America Validator Network)", "ETH Staking", "Crypto Holdings"]
  },
  "keyMetrics": [
    {
      "name": "P/NAV",
      "value": "0.82x",
      "interpretation": "MSTR P/B 2-3x 대비 NAV 18% 할인 거래. 자산가치보다 싸게 거래되는 상태 지속"
    },
    {
      "name": "ETH 보유량",
      "value": "4,660,903 ETH",
      "interpretation": "전체 ETH 공급량(120.7M)의 3.86%. 상장 기업 중 세계 최대. 6M ETH(5%) 목표까지 134만 ETH 추가 필요"
    },
    {
      "name": "크립토 공포탐욕 지수",
      "value": "12 (극단적 공포)",
      "interpretation": "공포탐욕 지수 12는 극심한 공포 상태. BTC $66,000, ETH $2,000 근처. 역사적으로 극단적 공포는 반등의 전조가 되기도 했다"
    },
    {
      "name": "배당수익률",
      "value": "5.1%",
      "interpretation": "주가 하락으로 배당수익률 상승. S&P 500 평균 1.3%, 크립토 관련 주식 중 유일한 배당주"
    },
    {
      "name": "스테이킹 매출(예상)",
      "value": "연 $300M+",
      "interpretation": "MAVAN 전면 이관 시 기준. 3/25 론칭 후 3.14M ETH($6.29B) 스테이킹. 수수료 절감 효과"
    },
    {
      "name": "ETH 현재가",
      "value": "~$2,000",
      "interpretation": "$2,000 심리적 지지선에서 아슬아슬하게 버티는 중. 주말 크립토 시장 전반 극단적 공포. 이탈 시 NAV 급감 불가피"
    }
  ],
  "growthDrivers": [
    {
      "title": "BeInCrypto: '$300M 스테이킹 수익에도 주가는 고전' (3/27)",
      "description": "MAVAN 론칭으로 연 $300M 스테이킹 매출 전망. mNAV 1.0x까지 하락. 스테이킹 수익이 본격화되면 주가 재평가 가능성"
    },
    {
      "title": "B. Riley 목표가 상향, Strong Buy (3/26)",
      "description": "MAVAN 론칭 이후 B. Riley가 목표가를 $34.50으로 상향. 현재가 대비 +87.6% 상승 여력"
    },
    {
      "title": "MAVAN 스테이킹 플랫폼 정식 론칭 (3/25)",
      "description": "3.14M ETH($6.29B)를 Coinbase에서 자체 MAVAN으로 이관. 제3자 수수료 절감으로 연 $300M+ 매출 목표"
    },
    {
      "title": "Tom Lee 'Alchemy of 5%': ETH 공급량 5% 목표 (3/24)",
      "description": "6M ETH 확보 목표. 현재 3.86%로 72% 달성. 5% 달성 시 이더리움 생태계 내 실질적 영향력 확보"
    },
    {
      "title": "하락장 속 $138M ETH 추가 매수 (3/23)",
      "description": "Tom Lee: 'crypto winter는 거의 끝났다'. 65,341 ETH 추가 매수. 하락장에서도 공격적 매수 지속"
    }
  ],
  "competitiveAdvantage": {
    "summary": "상장 기업 중 최대 ETH 보유량(3.86% of supply). Tom Lee 합류로 제도권 신뢰도 확보. MicroStrategy의 BTC 전략을 ETH에 적용한 유일한 대규모 플레이어.",
    "moats": [
      {
        "type": "ETH 공급량 집중",
        "description": "전체 ETH 공급의 3.86% 보유. 시장에서 대체 불가능한 포지션."
      },
      {
        "type": "제도권 접근성",
        "description": "상장 주식으로 ETH 노출 제공. ETF 없이도 기관 투자자 접근 가능."
      },
      {
        "type": "MAVAN 자체 스테이킹",
        "description": "3.14M ETH 자체 스테이킹 + MAVAN 플랫폼으로 수수료 절감 및 수익률 우위."
      }
    ],
    "competitors": [
      {
        "name": "MicroStrategy (MSTR)",
        "detail": "Bitcoin 트레저리 전략의 원조. BTC 집중 vs BMNR의 ETH 집중. MSTR BTC 721,000개($51B)"
      },
      {
        "name": "Grayscale Ethereum Trust (ETHE)",
        "detail": "ETH ETF 경쟁. 수수료 구조 차이"
      },
      {
        "name": "Coinbase (COIN)",
        "detail": "거래소 기반 크립토 노출. 사업 모델 근본적 차이"
      }
    ]
  },
  "recentNews": [
    {
      "date": "2026-03-28",
      "headline": "크립토 시장 극단적 공포: BTC $66,000, 공포탐욕 지수 12",
      "significance": "BTC가 24.6% YTD 하락, 2025년 10월 고점($126K) 대비 -48%. ETH $2,000 직전. 극단적 공포는 역사적으로 반등 전조가 되기도 했다",
      "url": "https://blockchainmagazine.net/crypto-market-today-2026-03-28/"
    },
    {
      "date": "2026-03-27",
      "headline": "BeInCrypto: '$300M 스테이킹 수익에도 BMNR 주가는 고전'",
      "significance": "MAVAN 론칭으로 연 $300M 매출 전망이지만 mNAV 1.0x까지 하락. ETH 약세가 스테이킹 호재를 상쇄하는 구도",
      "url": "https://beincrypto.com/bitmine-bmnr-300m-staking-revenue-price-struggles/"
    },
    {
      "date": "2026-03-27",
      "headline": "BMNR -5.34% 급락, $18.39 마감. $20 지지선 완전 붕괴",
      "significance": "$18.39로 $20 지지선 완전 붕괴. 7주간 횡보하던 기술적 지지가 무너졌다",
      "url": "https://finance.yahoo.com/quote/BMNR/"
    },
    {
      "date": "2026-03-26",
      "headline": "B. Riley 목표가 상향, Strong Buy $34.50",
      "significance": "MAVAN 론칭 이후 B. Riley가 목표가를 $34.50으로 상향. 현재가 대비 +87.6% 상승 여력",
      "url": "https://www.marketbeat.com/stocks/NYSEAMERICAN/BMNR/forecast/"
    },
    {
      "date": "2026-03-25",
      "headline": "MAVAN(Made in America Validator Network) 정식 론칭",
      "significance": "자체 ETH 스테이킹 플랫폼 MAVAN 론칭. 3.14M ETH($6.29B)를 Coinbase에서 이관. 연 $300M+ 매출 목표",
      "url": "https://www.prnewswire.com/news-releases/bitmine-immersion-technologies-bmnr-announces-launch-of-mavan-made-in-america-validator-network-the-companys-proprietary-staking-solution-302724419.html"
    }
  ],
  "analystOpinions": {
    "consensusTarget": 34.5,
    "highTarget": 34.5,
    "lowTarget": 30,
    "upsidePercent": 87.6,
    "buyCount": 1,
    "holdCount": 0,
    "sellCount": 0,
    "notableComment": "B. Riley Strong Buy $34.50. 주가 하락으로 상승 여력이 87.6%로 확대. 크립토 공포탐욕 지수 12(극단적 공포) 속에서 펀더멘털 기반 커버리지 유지"
  },
  "risks": [
    {
      "severity": "critical",
      "title": "크립토 극단적 공포, ETH $2,000 이탈 위기",
      "description": "공포탐욕 지수 12(극단적 공포). BTC $66,000(-48% from peak), ETH $2,000 직전. 주말 크립토 셀오프가 지속되면 $2,000 이탈로 BMNR NAV 급감 불가피"
    },
    {
      "severity": "critical",
      "title": "$20 지지선 붕괴, 기술적 약세 심화",
      "description": "$18.39로 $20 지지선 완전 붕괴. 7주간 횡보하던 기술적 지지가 무너졌다. 다음 지지선 $15 부근"
    },
    {
      "severity": "high",
      "title": "mNAV 1.0x, 프리미엄 완전 소멸",
      "description": "BeInCrypto 기준 mNAV 1.0x. 시장이 BMNR에 어떤 프리미엄도 부여하지 않는 상황. MSTR은 P/B 2-3x"
    },
    {
      "severity": "medium",
      "title": "이란-이스라엘 분쟁이 위험자산 압박",
      "description": "지정학 리스크로 위험자산 전반 셀오프. 크립토는 위험자산 중에서도 가장 민감하게 반응"
    },
    {
      "severity": "medium",
      "title": "스테이킹 수익 현실화까지 시간 소요",
      "description": "MAVAN 론칭했지만 Coinbase에서 전면 이관까지 수개월 소요 전망. 단기 매출 효과 제한적"
    }
  ],
  "buyReasons": [
    {
      "title": "P/NAV 0.82x, 극단적 공포 속 자산 할인",
      "rationale": "NAV $10.5B 대비 시총 $8.6B. 공포탐욕 지수 12에서의 매수는 역사적으로 높은 수익률을 보였다. 극단적 공포가 반등의 전조가 될 수 있다"
    },
    {
      "title": "B. Riley Strong Buy $34.50(+87.6%)",
      "rationale": "MAVAN 론칭 후 목표가 상향. 주가 하락으로 상승 여력이 87.6%까지 확대. 펀더멘털 기반 커버리지 유지"
    },
    {
      "title": "MAVAN 론칭으로 수익 모델 전환",
      "rationale": "3.14M ETH 자체 스테이킹으로 연 $300M+ 매출 목표. 보유에서 수익 창출 기업으로 전환 중"
    },
    {
      "title": "배당 5.1%로 하락 방어 + 경영진 확신",
      "rationale": "크립토 주식 중 유일한 배당주. Tom Lee가 하락장에서 $138M 추가 매수. 경영진의 강한 확신"
    }
  ],
  "technicalPosition": {
    "week52High": 161.0,
    "week52Low": 3.2,
    "currentPositionPercent": 9.6,
    "sma50": 23.0,
    "sma50Signal": "below",
    "sma200": 32,
    "sma200Signal": "below",
    "rsi": 38,
    "rsiSignal": "neutral"
  },
  "overallOpinion": [
    "크립토 시장이 극단적 공포(지수 12)에 빠져있다. BTC $66,000, ETH $2,000 직전. 이란-이스라엘 분쟁과 매크로 악재가 위험자산을 짓누르고 있다. 주말 크립토 셀오프가 BMNR의 NAV를 계속 위협하고 있다",
    "$20 지지선이 붕괴됐고 mNAV 1.0x로 시장이 프리미엄을 전혀 안 주고 있다. 하지만 역사적으로 공포탐욕 지수 10-15 구간은 장기 반등의 시작점이 되기도 했다",
    "B. Riley는 $34.50(+87.6%)을 유지하고 있고, MAVAN의 연 $300M 매출 잠재력은 건재하다. P/NAV 0.82x에 배당 5.1%는 장기 투자자에게 매력적",
    "$18.39, RSI 38. ETH $2,000 사수 여부가 모든 것을 결정한다. Buy, 리스크 감내 가능한 소액 분할매수만 유효"
  ],
  "investmentVerdict": {
    "stance": "buy",
    "summary": "극단적 공포(지수 12)에서 P/NAV 0.82x, B. Riley $34.50(+87.6%), 배당 5.1%. MAVAN $300M 매출 전환 진행 중. 단기 ETH $2,000 이탈 리스크는 크지만 극단적 공포는 역설적으로 장기 매수 기회. 리스크 관리 필수, 소액 분할매수만",
    "horizon": "6-12개월"
  },
  "sources": [
    {
      "name": "BlockchainMagazine - 크립토 공포탐욕 지수 12",
      "url": "https://blockchainmagazine.net/crypto-market-today-2026-03-28/",
      "description": "BTC $66,350, 공포탐욕 12(극단적 공포), 시총 $2.37T"
    },
    {
      "name": "FX Leaders - BTC $66,000 지지",
      "url": "https://www.fxleaders.com/news/2026/03/28/bitcoin-price-prediction-66000-support-braced-as-extreme-fear-grips-the-market/",
      "description": "BTC $66,000-$66,500, 24시간 -3-4% 하락"
    },
    {
      "name": "BeInCrypto - BMNR $300M 스테이킹 분석",
      "url": "https://beincrypto.com/bitmine-bmnr-300m-staking-revenue-price-struggles/",
      "description": "mNAV 1.0x, $300M 스테이킹 매출 전망과 주가 괴리 분석"
    },
    {
      "name": "MarketBeat - BMNR Forecast",
      "url": "https://www.marketbeat.com/stocks/NYSEAMERICAN/BMNR/forecast/",
      "description": "B. Riley Strong Buy $34.50"
    },
    {
      "name": "PRNewswire - MAVAN 론칭 공시",
      "url": "https://www.prnewswire.com/news-releases/bitmine-immersion-technologies-bmnr-announces-launch-of-mavan-made-in-america-validator-network-the-companys-proprietary-staking-solution-302724419.html",
      "description": "MAVAN 스테이킹 플랫폼 정식 론칭, 3.14M ETH"
    },
    {
      "name": "CoinCentral - Tom Lee $138M ETH 매수",
      "url": "https://coincentral.com/bitmine-bmnr-stock-jumps-3-as-tom-lee-bets-138m-more-on-eth-recovery/",
      "description": "65,341 ETH($138M) 추가 매수, crypto winter 발언"
    },
    {
      "name": "LatestLY - BTC $66,008, YTD -24.6%",
      "url": "https://www.latestly.com/business/bitcoin-price-today-march-28-2026-btc-price-at-usd-66000-amid-geopolitical-tensions-7370331.html",
      "description": "BTC 지정학 긴장 속 $66,000, 기관 매수 흡수 중"
    },
    {
      "name": "StockAnalysis - BMNR",
      "url": "https://stockanalysis.com/stocks/bmnr/",
      "description": "종합 재무 분석, 밸류에이션, ETH 보유 현황"
    }
  ],
  "snsContent": {
    "x": {
      "hook": "BMNR $18.39 | 크립토 공포지수 12, 극단적 공포 속 기회인가",
      "text": "$BMNR $18.39 (주말, 금요일 종가)\n\n크립토 공포탐욕 지수 12(극단적 공포). BTC $66K, ETH $2,000 직전. $20 붕괴 상태.\n\nP/NAV 0.82x, 배당 5.1%\nB. Riley $34.50(+87.6%)\n\n1/4",
      "thread": [
        "역사적으로 공포지수 10-15 구간은 장기 반등 시작점이 되기도 했다.\nMSTR은 BTC 공포 때 2-3배 반등.\n\nBMNR도 ETH 회복 시 레버리지 반등 가능\n\n2/4",
        "MAVAN 론칭 4일차. 연 $300M+ 매출 목표.\nTom Lee: $138M ETH 추가 매수.\n6M ETH(5%) 목표까지 72% 달성.\n\n공포 속에서도 매수 지속\n\n3/4",
        "리스크: ETH $2,000 이탈 시 NAV 급감.\n88% ETH 집중, 다음 지지 $15.\n\nBuy. 리스크 감내 가능한 소액만. ETH $2,000이 생명선\n\n4/4"
      ]
    },
    "threads": {
      "hook": "BMNR: 크립토 공포지수 12, 극단적 공포에서 반등을 기다린다",
      "text": "$BMNR $18.39 (주말)\n\n크립토 공포탐욕 지수 12(극단적 공포). BTC $66K(-48% from peak), ETH $2,000 직전. 이란 분쟁이 위험자산을 짓누르고 있다.\n\n$20 붕괴에 mNAV 1.0x. 시장이 프리미엄을 전혀 안 주고 있다. 하지만 B. Riley $34.50(+87.6%), P/NAV 0.82x, 배당 5.1%.\n\n역사적으로 극단적 공포는 장기 반등의 전조. Tom Lee는 하락장에서 $138M을 더 넣었다.\n\nBuy, 소액 분할매수만. ETH $2,000이 핵심."
    },
    "telegram": {
      "hook": "BMNR 일일 분석 (3/29, 주말)",
      "text": "BMNR $18.39 (주말, 변동 제한적) | 시총 $8.6B | P/NAV 0.82x\nETH ~$2,000 | BTC $66K | 공포탐욕 12 | 배당 5.1%\n\n크립토 시장\n- 공포탐욕 지수 12 (극단적 공포)\n- BTC -48% from peak, ETH $2,000 직전\n- 이란 분쟁으로 위험자산 셀오프\n\n기업 현황\n- $20 지지선 붕괴, mNAV 1.0x\n- B. Riley $34.50 Strong Buy (+87.6%)\n- MAVAN 론칭 4일차, 연 $300M 목표\n\n리스크\n- ETH $2,000 이탈 시 NAV 급감\n- 88% ETH 집중, 다음 지지 $15\n\n판단: Buy (소액 분할매수, ETH $2,000 사수 전제)"
    },
    "tones": {
      "x": {
        "fact": {
          "hook": "BMNR $18.39 | 크립토 공포지수 12, 극단적 공포 속 기회인가",
          "text": "$BMNR $18.39 (주말, 금요일 종가)\n\n크립토 공포탐욕 지수 12(극단적 공포). BTC $66K, ETH $2,000 직전. $20 붕괴 상태.\n\nP/NAV 0.82x, 배당 5.1%\nB. Riley $34.50(+87.6%)\n\n1/4",
          "thread": [
            "역사적으로 공포지수 10-15 구간은 장기 반등 시작점이 되기도 했다.\nMSTR은 BTC 공포 때 2-3배 반등.\n\nBMNR도 ETH 회복 시 레버리지 반등 가능\n\n2/4",
            "MAVAN 론칭 4일차. 연 $300M+ 매출 목표.\nTom Lee: $138M ETH 추가 매수.\n6M ETH(5%) 목표까지 72% 달성.\n\n공포 속에서도 매수 지속\n\n3/4",
            "리스크: ETH $2,000 이탈 시 NAV 급감.\n88% ETH 집중, 다음 지지 $15.\n\nBuy. 리스크 감내 가능한 소액만. ETH $2,000이 생명선\n\n4/4"
          ]
        },
        "witty": {
          "hook": "공포지수 12. 다들 도망갈 때 Tom Lee는 $138M을 더 넣었다",
          "text": "$BMNR $18.39 (주말)\n\n크립토 공포탐욕 12. 시장이 패닉인데 Tom Lee는 하락장에서 $138M ETH를 더 샀다.\n\n버핏: '남들이 두려워할 때 탐욕스러워라'\nTom Lee: '실행 중'\n\n1/4",
          "thread": [
            "만원짜리를 8,200원에 파는 중(P/NAV 0.82x).\n배당은 5.1%. 크립토에서 배당이라니.\nB. Riley: '$34.50 간다' (+87.6%)\n\n시장 vs 애널리스트, 극한 괴리\n\n2/4",
            "ETH $2,000. 이게 깨지면 다 같이 간다.\n안 깨지면? 레버리지 반등.\n\n극단적 공포가 극단적 수익의 시작점이기도 하다\n\n3/4",
            "MAVAN 4일차. $300M 매출 목표는 그대로.\n공포 속에서 수익 모델이 돌아가기 시작했다.\n\nBuy. 심장이 튼튼한 사람만\n\n4/4"
          ]
        },
        "empathy": {
          "hook": "BMNR 홀더들, 공포지수 12. 정말 무섭죠. 근데 이럴 때가 기회였어요",
          "text": "$BMNR $18.39 (주말)\n\n공포탐욕 지수 12. BTC $66K, ETH $2,000 직전. $20도 무너졌고. 정말 무서운 시간이에요.\n\n하지만 이런 극단적 공포가 기회가 되기도 했어요\n\n1/4",
          "thread": [
            "B. Riley는 $34.50을 유지하고 있어요(+87.6%).\nTom Lee는 $138M을 더 넣었고요.\nP/NAV 0.82x, 배당 5.1%.\n\n펀더멘털은 무너지지 않았어요\n\n2/4",
            "MAVAN이 돌아가기 시작했어요. $300M 매출 목표.\n공포 속에서도 회사는 수익 모델을 만들고 있어요.\n\n시간이 답을 줄 거예요\n\n3/4",
            "ETH $2,000이 핵심이에요.\n무리한 추매는 절대 안 돼요.\n감당 가능한 소액으로만. 건강이 먼저입니다.\n\nBuy, 리스크 관리 필수\n\n4/4"
          ]
        }
      },
      "threads": {
        "fact": {
          "hook": "BMNR: 크립토 공포지수 12, 극단적 공포에서 반등을 기다린다",
          "text": "$BMNR $18.39 (주말)\n\n크립토 공포탐욕 지수 12(극단적 공포). BTC $66K(-48% from peak), ETH $2,000 직전. 이란 분쟁이 위험자산을 짓누르고 있다.\n\n$20 붕괴에 mNAV 1.0x. 시장이 프리미엄을 전혀 안 주고 있다. 하지만 B. Riley $34.50(+87.6%), P/NAV 0.82x, 배당 5.1%.\n\n역사적으로 극단적 공포는 장기 반등의 전조. Tom Lee는 하락장에서 $138M을 더 넣었다.\n\nBuy, 소액 분할매수만. ETH $2,000이 핵심."
        },
        "witty": {
          "hook": "공포지수 12에 Tom Lee는 $138M을 더 넣었다. 미친 건가, 천재인가",
          "text": "$BMNR $18.39 (주말)\n\n크립토 공포 12. 시장이 패닉. BTC $66K, ETH $2,000.\n\nTom Lee는 이 타이밍에 $138M ETH를 더 샀다. 만원짜리를 8,200원에 파는데(P/NAV 0.82x) 배당도 5.1%. B. Riley는 $34.50(+87.6%).\n\n극단적 공포가 극단적 수익의 시작인지, 아니면 진짜 끝의 시작인지. ETH $2,000이 그 답을 정한다.\n\nBuy, 심장 강한 사람만."
        },
        "empathy": {
          "hook": "BMNR 홀더 여러분, 공포지수 12. 무섭지만, 이런 때가 기회였어요",
          "text": "$BMNR $18.39. 크립토 공포탐욕 12. $20도 깨졌고 ETH $2,000 직전.\n\n정말 무서운 주말이시죠. 52주 고점 $161 대비 -89%. 오래 참아오셨어요.\n\n하지만 B. Riley는 $34.50(+87.6%)을 유지하고 Tom Lee는 $138M을 더 넣었어요. MAVAN이 돌아가기 시작했고 배당 5.1%.\n\n역사적으로 이런 극단적 공포에서 매수한 사람이 가장 큰 수익을 거뒀어요. 리스크 관리 하면서 소액만. 건강이 먼저입니다."
        }
      }
    }
  }
}