{
  "symbol": "BMNR",
  "companyName": "Bitmine Immersion Technologies, Inc.",
  "analysisDate": "2026-03-30",
  "currentPrice": 18.39,
  "marketCap": "$8.6B",
  "businessSummary": {
    "oneLiner": "World's largest publicly traded Ethereum holder, applying MicroStrategy's Bitcoin playbook to Ethereum as a digital asset treasury company",
    "description": "Originally a Bitcoin mining company, pivoted to an Ethereum treasury strategy after Tom Lee (Fundstrat co-founder) joined. Holds 4,660,903 ETH (3.86% of total supply) with total crypto+cash of $10.9B. Launched MAVAN staking platform targeting $300M+ annual revenue. ETH battling around $2,000 creates extreme NAV volatility.",
    "howTheyMakeMoney": [
      "ETH Treasury: 4,660,903 ETH (~$9.3B at ~$2,004/ETH)",
      "ETH Staking Revenue: 3,142,643 ETH staked, targeting ~$300M/year via MAVAN",
      "Dividend: 5.1% yield, only dividend-paying crypto treasury company",
      "Bitcoin Holdings: 196 BTC (ancillary)"
    ],
    "keyProducts": [
      "Ethereum Treasury",
      "MAVAN (Made in America Validator Network)",
      "ETH Staking",
      "Crypto Holdings"
    ]
  },
  "keyMetrics": [
    {
      "name": "P/NAV",
      "value": "0.83x (est.)",
      "interpretation": "At ETH $2,004, estimated NAV ~$10.3B. Market cap $8.6B represents 17% discount. vs MSTR P/B of 2-3x"
    },
    {
      "name": "ETH Holdings",
      "value": "4,660,903 ETH",
      "interpretation": "3.86% of total ETH supply (120.7M). Largest public holder. 1.34M ETH needed to reach 6M (5%) target"
    },
    {
      "name": "ETH Current Price",
      "value": "~$2,004",
      "interpretation": "Slight recovery from $1,986 over the weekend. Back above $2,000 psychological level but still unstable"
    },
    {
      "name": "Dividend Yield",
      "value": "5.1%",
      "interpretation": "Yield increased due to share price decline. vs S&P 500 avg 1.3%. Only dividend-paying crypto stock"
    },
    {
      "name": "Staking Revenue (est.)",
      "value": "$300M+/year",
      "interpretation": "Based on full MAVAN migration. 3.14M ETH ($6.3B) staked since 3/25 launch"
    },
    {
      "name": "Daily Trading Volume",
      "value": "$1.2B (5-day avg)",
      "interpretation": "101st most traded stock in the US. Excellent liquidity"
    }
  ],
  "growthDrivers": [
    {
      "title": "BeInCrypto: '$300M staking revenue but stock struggles' (3/27)",
      "description": "MAVAN launch targets $300M annual staking revenue. mNAV at 1.0x. Potential re-rating when staking income materializes"
    },
    {
      "title": "B. Riley raises target, Strong Buy (3/26)",
      "description": "Post-MAVAN launch, B. Riley raised target to $34.50. 87.6% upside from current price"
    },
    {
      "title": "MAVAN staking platform officially launches (3/25)",
      "description": "3.14M ETH ($6.3B) migrated from Coinbase to proprietary MAVAN platform. Eliminates third-party fees targeting $300M+ annual revenue"
    },
    {
      "title": "Tom Lee 'Alchemy of 5%': targeting 5% of ETH supply (3/24)",
      "description": "6M ETH target. Currently at 3.86% (72% complete). At 5%, achieves meaningful influence within the Ethereum ecosystem"
    },
    {
      "title": "$138M ETH purchase during downturn (3/23)",
      "description": "Tom Lee: 'crypto winter is almost over.' Bought 65,341 ETH. Aggressive accumulation continues in bear market"
    }
  ],
  "competitiveAdvantage": {
    "summary": "Largest public ETH holdings (3.86% of supply). Tom Lee brings institutional credibility. Only large-scale player applying MSTR's BTC strategy to ETH.",
    "moats": [
      {
        "type": "ETH Supply Concentration",
        "description": "3.86% of total ETH supply. Irreplaceable position in the market"
      },
      {
        "type": "Institutional Access",
        "description": "Provides ETH exposure via publicly traded stock. Institutional access without ETF"
      },
      {
        "type": "Proprietary Staking",
        "description": "3.14M ETH self-staked via MAVAN platform. Fee savings and yield advantage"
      }
    ],
    "competitors": [
      {
        "name": "MicroStrategy (MSTR)",
        "detail": "Pioneer of BTC treasury strategy. BTC-focused vs BMNR's ETH focus. MSTR holds 721,000 BTC ($51B)"
      },
      {
        "name": "Grayscale Ethereum Trust (ETHE)",
        "detail": "ETH ETF competition. Different fee structure"
      },
      {
        "name": "Coinbase (COIN)",
        "detail": "Exchange-based crypto exposure. Fundamentally different business model"
      }
    ]
  },
  "recentNews": [
    {
      "date": "2026-03-30",
      "headline": "ETH recovers slightly to $2,004, back above $2,000 psychological level",
      "significance": "Weekend rebound from $1,986 to $2,004. Back above $2,000 but still in a tug-of-war zone. Changelly forecasts $2,056 by 3/31",
      "url": "https://changelly.com/blog/ethereum-eth-price-predictions/"
    },
    {
      "date": "2026-03-29",
      "headline": "ETH battles $2,000, weekly decline of -1.48%",
      "significance": "ETH oscillating around $2,000 with no clear direction heading into the weekend",
      "url": "https://bitcoinethereumnews.com/ethereum/eth-drops-1-48-as-key-level-breaks/"
    },
    {
      "date": "2026-03-27",
      "headline": "BeInCrypto: '$300M staking revenue but BMNR stock struggles'",
      "significance": "MAVAN launch targets $300M annual revenue but mNAV collapsed to 1.0x. ETH weakness offsets staking tailwind",
      "url": "https://beincrypto.com/bitmine-bmnr-300m-staking-revenue-price-struggles/"
    },
    {
      "date": "2026-03-26",
      "headline": "B. Riley raises target to $34.50, Strong Buy",
      "significance": "Post-MAVAN launch upgrade. 87.6% upside from current price",
      "url": "https://www.marketbeat.com/stocks/NYSEAMERICAN/BMNR/forecast/"
    },
    {
      "date": "2026-03-25",
      "headline": "MAVAN officially launches, 3.14M ETH self-staking begins",
      "significance": "Migration from Coinbase to proprietary MAVAN platform. US-based institutional-grade Ethereum staking",
      "url": "https://www.stocktitan.net/news/BMNR/bitmine-immersion-technologies-bmnr-announces-launch-of-mavan-made-f2jf4rl8rxac.html"
    }
  ],
  "analystOpinions": {
    "consensusTarget": 34.5,
    "highTarget": 34.5,
    "lowTarget": 30,
    "upsidePercent": 87.6,
    "buyCount": 1,
    "holdCount": 0,
    "sellCount": 0,
    "notableComment": "B. Riley Strong Buy at $34.50. Limited analyst coverage reduces reliability. ETH $2,000 instability is the key variable for target reassessment"
  },
  "risks": [
    {
      "severity": "critical",
      "title": "ETH $2,000 support unstable, further downside open",
      "description": "ETH recovered to $2,004 but is oscillating around $2,000. First breach below $2,000 since mid-2024. Technical analysis suggests $1,750 support. With 88% portfolio in ETH, still an existential threat to BMNR"
    },
    {
      "severity": "critical",
      "title": "$20 support fully broken, next support at $15",
      "description": "$18.39 after $20 support collapsed. Seven weeks of consolidation at $20 broke down. $15 next if ETH weakens further"
    },
    {
      "severity": "high",
      "title": "NAV erosion in progress",
      "description": "ETH holdings worth ~$9.3B at $2,004. NAV gap to market cap narrowing. Re-breach below $2,000 would accelerate erosion"
    },
    {
      "severity": "high",
      "title": "Broad crypto selloff environment",
      "description": "Iran-Israel geopolitical risks and global risk-off sentiment persist. Crypto Fear & Greed Index at 12 (Extreme Fear)"
    },
    {
      "severity": "medium",
      "title": "Staking revenue realization takes time",
      "description": "MAVAN launched but full Coinbase migration expected to take months. Near-term revenue impact limited"
    }
  ],
  "buyReasons": [
    {
      "title": "17% discount to NAV, trading below asset value",
      "rationale": "At ETH $2,004, NAV ~$10.3B vs $8.6B market cap (17% discount). Extreme discount compared to MSTR's P/B of 2-3x"
    },
    {
      "title": "B. Riley Strong Buy, $34.50 target (+87.6%)",
      "rationale": "Post-MAVAN target raise. Price decline expanded upside to 87.6%"
    },
    {
      "title": "MAVAN transforms revenue model",
      "rationale": "3.14M ETH self-staked targeting $300M+ annual revenue. Transitioning from pure holder to revenue generator"
    },
    {
      "title": "5.1% dividend yield as downside protection",
      "rationale": "Only dividend-paying crypto stock. Yield rose to 5.1% on share price decline"
    },
    {
      "title": "ETH recovery attempt, potential bottom formation",
      "rationale": "ETH rebounded from $1,986 to $2,004 over the weekend. Post-capitulation bounce attempt. Fast recovery possible if buying returns"
    }
  ],
  "technicalPosition": {
    "week52High": 161.0,
    "week52Low": 3.2,
    "currentPositionPercent": 9.6,
    "sma50": 23.0,
    "sma50Signal": "below",
    "sma200": 32,
    "sma200Signal": "below",
    "rsi": 38,
    "rsiSignal": "neutral"
  },
  "overallOpinion": [
    "ETH recovered slightly from $1,986 to $2,004 over the weekend. Back above the $2,000 psychological level, but the tug-of-war continues with no clear directional resolution yet",
    "For BMNR with 88% of its portfolio in ETH, this $2,000 battle is an existential one. Trading at a 17% NAV discount, but technical analysis showing $1,750 downside remains valid. Crypto Fear Index at 12 (Extreme Fear) says it all",
    "B. Riley Strong Buy $34.50 (+87.6%), MAVAN targeting $300M annual revenue, 5.1% dividend. Daily trading volume of $1.2B makes it the 101st most traded stock in the US. Fundamentals are intact",
    "ETH recovery attempt is positive but needs confirmation. Maintain existing positions, defer new purchases until ETH settles above $2,000. Hold"
  ],
  "investmentVerdict": {
    "stance": "hold",
    "summary": "ETH recovered slightly to $2,004 but the $2,000 tug-of-war continues. B. Riley's $34.50 target and MAVAN's $300M revenue projection remain valid, but caution is warranted until ETH direction is confirmed. Maintain positions, defer new buys until ETH stabilizes above $2,000",
    "horizon": "3-6 months (contingent on ETH recovery)"
  },
  "sources": [
    {
      "name": "Changelly - ETH Price Prediction",
      "url": "https://changelly.com/blog/ethereum-eth-price-predictions/",
      "description": "ETH at $2,003.85, forecasting $2,056 by 3/31"
    },
    {
      "name": "BitcoinEthereumNews - ETH -1.48%",
      "url": "https://bitcoinethereumnews.com/ethereum/eth-drops-1-48-as-key-level-breaks/",
      "description": "ETH price action around $2,000 key level"
    },
    {
      "name": "BeInCrypto - BMNR $300M staking analysis",
      "url": "https://beincrypto.com/bitmine-bmnr-300m-staking-revenue-price-struggles/",
      "description": "mNAV at 1.0x, $300M staking revenue outlook vs price weakness"
    },
    {
      "name": "MarketBeat - BMNR Forecast",
      "url": "https://www.marketbeat.com/stocks/NYSEAMERICAN/BMNR/forecast/",
      "description": "B. Riley Strong Buy at $34.50"
    },
    {
      "name": "StockTitan - MAVAN Launch",
      "url": "https://www.stocktitan.net/news/BMNR/bitmine-immersion-technologies-bmnr-announces-launch-of-mavan-made-f2jf4rl8rxac.html",
      "description": "MAVAN 3.14M ETH self-staking platform launch"
    },
    {
      "name": "PRNewswire - BMNR 4.661M ETH holdings",
      "url": "https://www.prnewswire.com/news-releases/bitmine-immersion-technologies-bmnr-announces-eth-holdings-reach-4-661-million-tokens-and-total-crypto-and-total-cash-holdings-of-11-0-billion-302721764.html",
      "description": "Daily volume $1.2B, 101st most traded US stock"
    },
    {
      "name": "StocksToTrade - BMNR price analysis",
      "url": "https://stockstotrade.com/news/bitmine-immersion-technologies-inc-bmnr-news-2026_03_27/",
      "description": "March price action and volatility patterns"
    },
    {
      "name": "247 Wall St - BMNR 5% ETH goal",
      "url": "https://247wallst.com/investing/2026/03/24/bitmine-immersion-nears-5-eth-goal-what-happens-then/",
      "description": "Tom Lee 5% ETH supply target analysis"
    }
  ],
  "snsContent": {
    "x": {
      "hook": "BMNR | ETH recovers to $2,004, $2,000 battle continues",
      "text": "$BMNR $18.39\n\nETH rebounded from $1,986 to $2,004. Back above $2,000 but still battling.\n\n88% of portfolio in ETH. This battle is BMNR's fate.\n\n1/4",
      "thread": [
        "17% discount to NAV. vs MSTR P/B of 2-3x.\n\nB. Riley $34.50 (+87.6%). MAVAN $300M/yr.\nDividend 5.1%. Fundamentals are there\n\n2/4",
        "But $1,750 downside still technically open.\nFear Index 12 (Extreme Fear).\n\nIs this a post-capitulation bounce\nor more downside ahead? No answer yet\n\n3/4",
        "Wait for ETH to settle above $2,000.\nMaintain positions, hold off on new buys.\n\nHold. Let ETH decide\n\n4/4"
      ]
    },
    "threads": {
      "hook": "BMNR: ETH recovers to $2,004, the $2,000 battle decides everything",
      "text": "$BMNR $18.39\n\nETH bounced from $1,986 to $2,004 over the weekend. Back above $2,000 but the tug-of-war continues.\n\n88% ETH portfolio. 17% NAV discount. B. Riley $34.50 (+87.6%). MAVAN $300M/yr. Dividend 5.1%.\n\nBut $1,750 downside open and Fear Index at 12. Is this capitulation bounce or more pain?\n\nHold. Wait for ETH to confirm above $2,000."
    },
    "telegram": {
      "hook": "BMNR Daily Analysis (3/30)",
      "text": "BMNR $18.39 | MCap $8.6B | Div 5.1%\nETH $2,004 (slight recovery) | Verdict: Hold\n\nKey Changes\n- ETH recovered from $1,986 to $2,004 over weekend\n- Back above $2,000, battle continues\n\nBullish\n- B. Riley $34.50 (+87.6%) Strong Buy\n- MAVAN $300M/yr revenue transition\n- 17% NAV discount\n- $1.2B daily volume (excellent liquidity)\n\nRisks\n- ETH $1,750 downside technically open\n- Fear Index 12 (Extreme Fear)\n- $20 support broken\n\nVerdict: Hold. Defer new buys until ETH settles above $2,000"
    },
    "tones": {
      "x": {
        "fact": {
          "hook": "BMNR | ETH recovers to $2,004, $2,000 battle continues",
          "text": "$BMNR $18.39\n\nETH rebounded from $1,986 to $2,004. Back above $2,000 but still battling.\n\n88% of portfolio in ETH. This battle is BMNR's fate.\n\n1/4",
          "thread": [
            "17% discount to NAV. vs MSTR P/B of 2-3x.\n\nB. Riley $34.50 (+87.6%). MAVAN $300M/yr.\nDividend 5.1%. Fundamentals are there\n\n2/4",
            "But $1,750 downside still technically open.\nFear Index 12 (Extreme Fear).\n\nIs this a post-capitulation bounce\nor more downside ahead? No answer yet\n\n3/4",
            "Wait for ETH to settle above $2,000.\nMaintain positions, hold off on new buys.\n\nHold. Let ETH decide\n\n4/4"
          ]
        },
        "witty": {
          "hook": "ETH climbed $18 over the weekend. BMNR holders rejoice? Not yet",
          "text": "$BMNR $18.39\n\nETH $2,004. It climbed $18 from $1,986.\n\nNot exactly a victory lap.\nStill stuck in the $2,000 no-man's land.\n\n1/4",
          "thread": [
            "Tom Lee says winter's ending.\nFear Index reads 12.\n\nOne says spring, the other says blizzard.\nWelcome to crypto\n\n2/4",
            "B. Riley $34.50 (+87.6%). MAVAN $300M.\nDividend 5.1%. NAV 17% discount.\n\nThe fundamentals look great on paper.\nETH just won't cooperate\n\n3/4",
            "ETH holds $2,000? Rebound.\nETH loses $2,000? $1,750 next.\n\nBMNR's destiny is ETH's to decide. Hold\n\n4/4"
          ]
        },
        "empathy": {
          "hook": "BMNR holders, ETH's slight bounce is a relief. But stay cautious",
          "text": "$BMNR $18.39\n\nETH at $2,004. A small bounce from $1,986. You're probably feeling a bit better, but $2,000 is still contested.\n\n1/4",
          "thread": [
            "17% NAV discount. B. Riley $34.50.\nMAVAN, 5.1% dividend.\n\nThe company's direction hasn't changed.\nJust need ETH to cooperate\n\n2/4",
            "Fear Index at 12. The market is terrified.\nMaking hasty decisions in fear\nrarely ends well\n\n3/4",
            "Wait for ETH to settle above $2,000.\nNo aggressive averaging down.\n\nHold. Patience is the play right now\n\n4/4"
          ]
        }
      },
      "threads": {
        "fact": {
          "hook": "BMNR: ETH recovers to $2,004, $2,000 battle decides fate",
          "text": "$BMNR $18.39\n\nETH bounced from $1,986 to $2,004. Back above $2,000 but tug-of-war continues. 88% ETH portfolio.\n\n17% NAV discount. B. Riley $34.50 (+87.6%). MAVAN $300M/yr. 5.1% dividend.\n\nETH $1,750 open. Fear Index 12. Hold. ETH confirmation needed."
        },
        "witty": {
          "hook": "ETH gained $18. Not exactly champagne territory for BMNR",
          "text": "$BMNR $18.39\n\nETH $2,004. Up $18 from $1,986. Celebration? Not quite. Still in the $2,000 twilight zone.\n\nTom Lee: 'Winter's ending.' Fear Index: 12. Someone's wrong.\n\nB. Riley $34.50, MAVAN $300M, dividend 5.1%. Fundamentals look great. ETH just won't cooperate.\n\nBMNR's destiny is ETH's to decide. Hold."
        },
        "empathy": {
          "hook": "BMNR shareholders, ETH's small bounce must be a relief. But this isn't over",
          "text": "$BMNR $18.39, ETH $2,004.\n\nA small bounce from $1,986. Relieving, but $2,000 is still a battlefield.\n\n17% NAV discount, B. Riley $34.50, MAVAN $300M, 5.1% dividend. The company is on track.\n\nFear Index at 12. Don't rush decisions in extreme fear. Wait for ETH to confirm above $2,000.\n\nHold. Patience is the strategy."
        }
      }
    }
  }
}