{
  "symbol": "TSLA",
  "companyName": "Tesla, Inc.",
  "analysisDate": "2026-03-30",
  "currentPrice": 361.83,
  "marketCap": "$1.16T",
  "businessSummary": {
    "oneLiner": "세계 최대 EV 제조사이자 자율주행, 로봇, 에너지, AI 칩을 아우르는 'Physical AI 플랫폼' 기업",
    "description": "테슬라는 전기차 판매를 넘어 FSD 자율주행, Cybercab 로보택시, Optimus 휴머노이드 로봇, Megapack 에너지 저장 등으로 사업을 확장 중이다. 2025년 연간 매출 948억 달러, GAAP EPS 1.08달러를 기록했으며, Q4 2025에서 매출총이익률 20.1%로 2년 만에 최고치를 달성했다. FSD는 월 99달러 구독 모델로 전환해 반복 매출을 극대화하고 있으며, 2026년 4월부터 Cybercab 양산, Roadster 공개 등 핵심 성장 촉매가 예정돼 있다.",
    "howTheyMakeMoney": [
      "전기차 판매 (Model 3/Y, Cybertruck)",
      "에너지 저장, 발전 (Megapack, Powerwall, 태양광)",
      "서비스, 충전 (Supercharger 네트워크, 보험, OTA 업그레이드)",
      "FSD(Full Self-Driving) 월 99달러 구독 및 라이선싱",
      "규제 크레딧 판매"
    ],
    "keyProducts": ["Model Y/3", "Cybertruck", "Cybercab", "Megapack 3", "FSD", "Optimus", "Terafab", "Roadster"]
  },
  "keyMetrics": [
    {
      "name": "P/E (TTM)",
      "value": "335x",
      "interpretation": "S&P 500 평균 약 23x, 자동차 섹터 평균 약 12x 대비 극단적 프리미엄. 52주 고점 대비 -27% 할인에도 여전히 극고배율"
    },
    {
      "name": "Forward P/E",
      "value": "174x",
      "interpretation": "2026년 EPS 전망 $2.08 기준. 성장주 평균 30-40x 대비 4배 이상 높음. 로보택시, 에너지 사업의 폭발적 성장이 선반영된 수치"
    },
    {
      "name": "2026년 인도 가이던스",
      "value": "169만대 (하향)",
      "interpretation": "기존 175만대에서 169만대로 하향 조정. 시위 확산과 유럽 판매 부진이 반영. 성장률 둔화 우려 심화"
    },
    {
      "name": "Q1 2026 인도량 컨센서스",
      "value": "365,645대",
      "interpretation": "23명 애널리스트 컨센서스. 전년 Q1(336,681대) 대비 +8%지만, Q4 2025(418,227대)보다 13% 감소"
    },
    {
      "name": "시가총액",
      "value": "$1.16T",
      "interpretation": "YTD -20%. 도요타, 폭스바겐, GM, 포드 합산보다 큰 규모이나 빠르게 축소 중"
    },
    {
      "name": "RSI (14일)",
      "value": "33",
      "interpretation": "과매도 기준선 30에 근접. 매도 압력이 극심하나 기술적 반등 가능성도 시사"
    }
  ],
  "growthDrivers": [
    {
      "title": "EV 시장 28% 급감 속 테슬라 시장점유율 50%+ 확대 (3/27)",
      "description": "전체 EV 시장이 28% 급감하는 가운데에도 테슬라는 시장점유율을 50% 이상으로 끌어올렸다. 경쟁사 대비 압도적 브랜드 파워와 충전 인프라가 불황기에 오히려 경쟁 우위로 작용"
    },
    {
      "title": "SpaceX IPO 준비 루머, 테슬라 밸류에이션 촉매 (3/25)",
      "description": "SpaceX가 IPO를 준비 중이라는 루머가 확산. SpaceX 주식을 보유한 테슬라 투자자들에게 간접적 촉매로 작용할 수 있으며, 머스크 생태계 전체의 가치 재평가 가능성"
    },
    {
      "title": "Optimus3 로봇 영상 공개, 올여름 생산 시작 (3/25)",
      "description": "테슬라가 Optimus3 휴머노이드 로봇의 감속기어와 정밀 손 설계 영상을 공개. 2026년 연말까지 100만 대 생산률 목표. Trefis는 로봇 사업의 가치를 $2-3조로 평가"
    },
    {
      "title": "Cybercab 4월 양산 + Roadster 4월 말 공개",
      "description": "핸들 없는 완전자율주행 로보택시 Cybercab 양산 시작과 차세대 Roadster 공개가 4월에 동시 예정. 단기간에 두 가지 대형 카탈리스트 집중"
    },
    {
      "title": "Terafab $25B AI 칩 공장, Wedbush '게임 체인저'",
      "description": "Wedbush가 Terafab 반도체 공장 계획을 '게임 체인저'라고 평가하며 $600 목표가를 재확인. AI5 칩 소량 생산 2026년 말 시작, 본격 양산은 2027년"
    },
    {
      "title": "NHTSA FSD 조사 심화, 규제 리스크 부상 (3/19)",
      "description": "NHTSA가 안개, 먼지 등 저시야 환경에서 FSD 성능 문제로 조사를 격상했다. Trefis는 이것이 '1조 달러 AI 테제'를 깨뜨릴 수 있다고 경고"
    }
  ],
  "competitiveAdvantage": {
    "summary": "미국 EV 시장 50%+ 점유율, FSD 84억 마일 데이터, Supercharger NACS 표준 장악, Terafab으로 AI 칩 내재화 추진",
    "moats": [
      {
        "type": "데이터 해자",
        "description": "FSD 84억 마일 실주행 데이터. 경쟁사가 단기간에 따라잡기 불가능한 규모의 자율주행 학습 데이터"
      },
      {
        "type": "충전 인프라",
        "description": "Supercharger 네트워크가 NACS 표준으로 채택. 포드, GM 등 경쟁사도 테슬라 충전 인프라 사용"
      },
      {
        "type": "수직 통합",
        "description": "배터리 셀, AI 칩(Terafab), 소프트웨어, 충전 인프라까지 수직 계열화. 원가 우위와 빠른 혁신 속도"
      },
      {
        "type": "브랜드 파워",
        "description": "EV 시장의 대명사. 높은 브랜드 인지도와 열성 팬층이 마케팅 비용 없이도 수요 창출"
      }
    ],
    "competitors": [
      {
        "name": "BYD",
        "detail": "중국 시장 1위, 유럽에서 100%+ 성장. 가격 경쟁력 우위로 테슬라를 빠르게 추격 중"
      },
      {
        "name": "Zoox (Amazon)",
        "detail": "SF, 라스베가스에서 로보택시 확대 중. 오스틴, 마이애미 시범 운행도 시작. 직접적 로보택시 경쟁자"
      },
      {
        "name": "Waymo (Alphabet)",
        "detail": "자율주행 상용화에서 테슬라 앞선 실적. 주당 20만+ 유료 탑승 달성. 로보택시 서비스 확대 중"
      },
      {
        "name": "현대/기아",
        "detail": "아이오닉, EV6 등으로 글로벌 EV 시장 점유율 확대. 가성비와 품질로 경쟁"
      }
    ]
  },
  "recentNews": [
    {
      "date": "2026-03-29",
      "headline": "테슬라, 2026년 인도 가이던스 175만대에서 169만대로 하향 조정",
      "significance": "Cathie Wood의 ARK가 테슬라 포지션을 줄였고, TipRanks는 테슬라가 2026년 인도 전망을 175만대에서 169만대로 낮췄다고 보도. 시위 확산과 유럽 판매 부진이 가이던스 하향의 주요 원인",
      "url": "https://www.tipranks.com/news/nvda-meta-tsla-amd-why-cathie-wood-is-trimming-these-big-tech-stocks"
    },
    {
      "date": "2026-03-29",
      "headline": "Simply Wall St: 연방 규제당국, FSD 카메라 온리 시스템 조사 착수",
      "significance": "저시야 환경(안개, 먼지)에서 FSD 성능을 집중 조사 중. 자율주행 밸류에이션의 핵심 리스크로 부각",
      "url": "https://simplywall.st/stocks/us/automobiles/nasdaq-tsla/tesla/news/tesla-autonomy-probe-tests-valuation-and-full-self-driving-p"
    },
    {
      "date": "2026-03-29",
      "headline": "Cathie Wood/ARK, 테슬라 포지션 축소, $84M 규모 기술주 매도",
      "significance": "ARK가 TSLA, NVDA, META, AMD 등을 동시에 매도. 테슬라의 가장 유명한 강세론자인 ARK의 매도는 심리적 충격",
      "url": "https://www.tipranks.com/news/nvda-meta-tsla-amd-why-cathie-wood-is-trimming-these-big-tech-stocks"
    },
    {
      "date": "2026-03-28",
      "headline": "'No Kings' 시위에 전세계 수백만명 참여, 테슬라 200건+ 타겟",
      "significance": "전세계 수천 건의 시위에 수백만명이 참여. 머스크의 DOGE 정치 활동으로 테슬라가 직접 시위 대상이 되었으며 200건 이상의 반테슬라 시위 진행",
      "url": "https://www.cbsnews.com/news/no-kings-rallies-protest-trump-millions/"
    },
    {
      "date": "2026-03-27",
      "headline": "EV 시장 28% 급감 속 테슬라 시장점유율 50%+ 달성",
      "significance": "전체 EV 시장이 급감하는 와중에도 테슬라는 점유율을 오히려 확대. 불황기에 강자가 더 강해지는 구조 증명",
      "url": "https://insideevs.com/news/tesla-ev-market-share-rises-slump/"
    }
  ],
  "analystOpinions": {
    "consensusTarget": 407,
    "highTarget": 600,
    "lowTarget": 119,
    "upsidePercent": 12.5,
    "buyCount": 17,
    "holdCount": 17,
    "sellCount": 9,
    "notableComment": "HSBC $119 최저 목표가 vs Stifel $508, Wedbush $600. 극단적 양극화 지속. ARK/Cathie Wood가 포지션을 줄인 것은 단기 신호로 주의 필요"
  },
  "risks": [
    {
      "severity": "critical",
      "title": "2026년 인도 가이던스 169만대로 하향, 성장 둔화 확인",
      "description": "기존 175만대에서 169만대로 하향 조정. 시위 확산과 유럽 판매 부진이 원인. ARK/Cathie Wood마저 포지션을 줄이면서 강세론의 대표 주자도 흔들리는 모습"
    },
    {
      "severity": "critical",
      "title": "'No Kings' 시위 확산, 소도시까지 번지는 반테슬라 운동",
      "description": "3/28 'No Kings Day 3.0' 시위 후 소도시 시위가 첫 동원 대비 40% 증가. 유럽 1월 등록 -17% 이미 확인됐고, 불매운동이 대도시를 넘어 소도시까지 확산되는 구조적 브랜드 위기"
    },
    {
      "severity": "critical",
      "title": "50일, 200일선 동시 이탈, RSI 33 과매도",
      "description": "50일선($387)과 200일선($400) 모두 아래에서 거래 중. RSI 33으로 과매도 근접. 5거래일 연속 하락"
    },
    {
      "severity": "high",
      "title": "HSBC 목표가 $119, ARK 매도 동시 발생",
      "description": "HSBC $119 재하향에 ARK까지 매도. 테슬라의 가장 유명한 강세론자(ARK)와 약세론자(HSBC)가 모두 부정적 행보를 보이는 이례적 상황"
    },
    {
      "severity": "high",
      "title": "FSD 규제 및 안전성 리스크 심화",
      "description": "NHTSA 조사 격상, 카메라 온리 시스템에 대한 규제당국 조사 착수. Trefis는 '1조 달러 AI 테제가 무너질 수 있다'고 경고"
    },
    {
      "severity": "high",
      "title": "극단적 밸류에이션 리스크",
      "description": "TTM P/E 335x로 S&P 500 평균 23x의 14.5배. 인도 가이던스까지 하향되면서 밸류에이션 정당화가 더 어려워졌다"
    }
  ],
  "buyReasons": [
    {
      "title": "EV 시장 침체 속 점유율 확대, 경쟁 우위 입증",
      "rationale": "EV 시장이 28% 급감하는 극한 환경에서도 테슬라 점유율은 50%+로 올라갔다. 불황일수록 강자가 더 강해지는 구조"
    },
    {
      "title": "4월 카탈리스트 집중 (Cybercab, Roadster, 4/21 실적)",
      "rationale": "Cybercab 양산, Roadster 공개, 네덜란드 FSD 승인, Q1 실적(4/21) 발표가 4월에 몰려 있어 단기 모멘텀 반전 가능성"
    },
    {
      "title": "RSI 33, 기술적 과매도 구간 진입",
      "rationale": "RSI가 30 과매도 기준선에 근접. 52주 고점 대비 -27% 할인. 단기 기술적 반등 가능성이 높아지는 구간"
    },
    {
      "title": "SpaceX IPO + Optimus 로봇, 장기 가치 재평가 촉매",
      "rationale": "SpaceX IPO 루머와 Optimus3 로봇 생산 시작이 테슬라의 장기 밸류에이션을 정당화하는 촉매로 작용 가능"
    }
  ],
  "technicalPosition": {
    "week52High": 498.83,
    "week52Low": 214.25,
    "currentPositionPercent": 51.8,
    "sma50": 387,
    "sma50Signal": "below",
    "sma200": 400,
    "sma200Signal": "below",
    "rsi": 33,
    "rsiSignal": "oversold"
  },
  "overallOpinion": [
    "테슬라가 2026년 인도 가이던스를 175만대에서 169만대로 낮췄다. 시위 확산과 유럽 부진이 가이던스에 직접 타격을 주기 시작했다. Cathie Wood의 ARK마저 테슬라를 줄이면서 강세론의 대표 주자도 흔들리고 있다",
    "HSBC $119 하향에 ARK 매도까지 겹쳤다. 약세론자와 강세론자가 동시에 부정적 행보를 보이는 이례적 상황. Stifel $508과의 5배 격차는 시장의 극단적 분열을 보여준다",
    "4월 카탈리스트가 3주 안에 집중돼 있다. Cybercab 양산, Roadster 공개, 4/21 실적. EV 시장 -28% 속 점유율 50%+를 지킨 체력은 건재하지만 가이던스 하향이 그 체력에 금이 갔다",
    "$361.83, RSI 33 과매도. 50일선($387), 200일선($400) 모두 아래. 인도 가이던스 하향으로 4/21 실적 눈높이도 낮아졌다. Hold, 4/21 확인이 더 중요해졌다"
  ],
  "investmentVerdict": {
    "stance": "hold",
    "summary": "인도 가이던스 169만대 하향과 ARK 매도는 기존 Hold 판단을 강화하는 신호다. RSI 33 과매도와 4월 카탈리스트 집중은 반등 근거지만, 시위 확산이 실제 가이던스에 영향을 주기 시작한 것이 확인됐다. 4/21 실적으로 가이던스 하향의 영향을 직접 확인해야 한다",
    "horizon": "3-6개월"
  },
  "sources": [
    {
      "name": "TipRanks - ARK 매도 및 인도 가이던스 하향",
      "url": "https://www.tipranks.com/news/nvda-meta-tsla-amd-why-cathie-wood-is-trimming-these-big-tech-stocks",
      "description": "테슬라 2026년 인도 전망 175만→169만대 하향, ARK $84M 기술주 매도"
    },
    {
      "name": "Simply Wall St - FSD 자율주행 조사",
      "url": "https://simplywall.st/stocks/us/automobiles/nasdaq-tsla/tesla/news/tesla-autonomy-probe-tests-valuation-and-full-self-driving-p",
      "description": "연방 규제당국 FSD 카메라 온리 시스템 조사 착수"
    },
    {
      "name": "Reuters - No Kings 시위, 소도시 참여 40% 증가",
      "url": "https://www.reuters.com/world/us/rallies-planned-thousands-us-cities-no-kings-protest-against-trump-2026-03-28/",
      "description": "소도시 시위 참여 40% 증가, 전국 확산 보도"
    },
    {
      "name": "TIKR - HSBC $119 목표가 하향",
      "url": "https://www.tikr.com/blog/hsbc-warns-tesla-nasdaq-tsla-stock-could-plunge-70-as-analysts-cut-price-targets",
      "description": "HSBC Reduce 등급, $133에서 $119로 목표가 추가 하향"
    },
    {
      "name": "Electrek - Q1 2026 인도량 컨센서스",
      "url": "https://electrek.co/2026/03/26/tesla-tsla-q1-2026-delivery-consensus-365000-analyst-estimates/",
      "description": "23명 애널리스트 Q1 컨센서스 365,645대"
    },
    {
      "name": "InsideEVs - EV 시장 28% 급감 속 테슬라 점유율 50%+",
      "url": "https://insideevs.com/news/tesla-ev-market-share-rises-slump/",
      "description": "테슬라가 EV 시장 침체 속에서도 점유율 확대"
    },
    {
      "name": "MarketBeat - TSLA 애널리스트 컨센서스",
      "url": "https://www.marketbeat.com/stocks/NASDAQ/TSLA/forecast/",
      "description": "컨센서스 목표가 $407"
    },
    {
      "name": "StockAnalysis - TSLA 주가 및 통계",
      "url": "https://stockanalysis.com/stocks/tsla/",
      "description": "종가 $361.83(-2.76%), P/E, 이동평균선, RSI 등 핵심 지표"
    },
    {
      "name": "Benzinga - EV 시장 침체 속 테슬라 승자",
      "url": "https://www.benzinga.com/trading-ideas/long-ideas/26/03/51522080/tesla-emerges-as-big-winner-in-brutal-28-ev-sales-slump",
      "description": "EV 판매 28% 감소 속 테슬라 점유율 확대 분석"
    }
  ],
  "snsContent": {
    "x": {
      "hook": "TSLA $362 | 인도 가이던스 하향, ARK마저 줄였다",
      "text": "$TSLA $361.83(-2.76%)\n\n2026년 인도 가이던스 175만→169만대로 하향.\nCathie Wood의 ARK마저 포지션을 줄였다.\n시위가 실제 숫자에 영향을 주기 시작했다.\n\n1/4",
      "thread": [
        "HSBC $119 하향에 ARK 매도까지.\n약세론자와 강세론자가 동시에 부정적.\n\nStifel $508과의 5배 격차.\n시장이 테슬라를 어디에 놔야 할지 모른다.\n\n2/4",
        "4월에 Cybercab, Roadster, 4/21 실적.\nEV -28% 속 점유율 50%+는 건재.\n\n하지만 가이던스 하향이\n그 체력에 금을 냈다.\n\n3/4",
        "RSI 33 과매도. 50일($387), 200일($400) 아래.\n컨센서스 $407(+12.5%).\n\nHold. 4/21 실적이 더 중요해졌다.\n\n4/4"
      ]
    },
    "threads": {
      "hook": "TSLA: 인도 가이던스 169만대 하향, ARK마저 줄였다",
      "text": "$TSLA $361.83(-2.76%), YTD -20%\n\n2026년 인도 가이던스가 175만대에서 169만대로 하향됐다. 시위 확산과 유럽 부진이 실제 숫자에 영향을 주기 시작했다.\n\nCathie Wood의 ARK마저 포지션을 줄였다. HSBC $119 하향과 동시에. 약세론자와 강세론자가 같은 방향을 가리키고 있다.\n\n4월 Cybercab, Roadster, 4/21 실적이 몰려 있다. EV -28% 속 점유율 50%+는 건재하지만 가이던스 하향은 무겁다.\n\nRSI 33 과매도. Hold. 4/21 실적 확인이 더 중요해졌다."
    },
    "telegram": {
      "hook": "TSLA 일일 분석 (3/30)",
      "text": "Tesla $361.83 (-2.76%) | 시총 $1.16T\nP/E 335x | Forward 174x | RSI 33\n\n핵심 변화\n- 2026년 인도 가이던스 175만→169만대 하향\n- Cathie Wood/ARK 포지션 축소\n- 연방 규제당국 FSD 카메라 조사 착수\n\n호재\n- EV 시장 -28% 속 점유율 50%+\n- 4월: Cybercab, Roadster, 4/21 실적\n- RSI 33 과매도 구간\n\n리스크\n- 가이던스 하향으로 성장 둔화 확인\n- HSBC $119 + ARK 매도 동시 발생\n- 시위 전국 확산\n\n기술적: 50일($387), 200일($400) 아래\n목표가: $407 (+12.5%)\n판단: Hold, 4/21 실적 확인 필수"
    },
    "tones": {
      "x": {
        "fact": {
          "hook": "TSLA $362 | 인도 가이던스 하향, ARK마저 줄였다",
          "text": "$TSLA $361.83(-2.76%)\n\n2026년 인도 가이던스 175만→169만대로 하향.\nCathie Wood의 ARK마저 포지션을 줄였다.\n시위가 실제 숫자에 영향을 주기 시작했다.\n\n1/4",
          "thread": [
            "HSBC $119 하향에 ARK 매도까지.\n약세론자와 강세론자가 동시에 부정적.\n\nStifel $508과의 5배 격차.\n시장이 테슬라를 어디에 놔야 할지 모른다.\n\n2/4",
            "4월에 Cybercab, Roadster, 4/21 실적.\nEV -28% 속 점유율 50%+는 건재.\n\n하지만 가이던스 하향이\n그 체력에 금을 냈다.\n\n3/4",
            "RSI 33 과매도. 50일($387), 200일($400) 아래.\n컨센서스 $407(+12.5%).\n\nHold. 4/21 실적이 더 중요해졌다.\n\n4/4"
          ]
        },
        "witty": {
          "hook": "ARK마저 줄였다. 테슬라 강세론의 마지막 보루가 흔들린다",
          "text": "$TSLA $361.83(-2.76%)\n\nCathie Wood가 테슬라를 줄였다.\n인도 가이던스는 175만→169만대.\n\n강세론의 대표 주자가 줄이면\n누가 남아서 살 건가?\n\n1/4",
          "thread": [
            "HSBC: $119. ARK: 매도.\n같은 날, 같은 방향.\n\n약세론자와 강세론자가 합의하는 건\n대개 나쁜 신호다.\n\n2/4",
            "EV 시장 -28%인데 점유율 50%+.\n이건 분명 대단한 건데,\n\n가이던스를 낮춰야 할 만큼\n시위가 실적에 들어왔다.\n\n3/4",
            "RSI 33. 4월에 모든 게 몰려 있다.\n\n반등할 수 있다. 하지만 지금은\n'지켜보자'가 '사자'보다 현명하다. Hold.\n\n4/4"
          ]
        },
        "empathy": {
          "hook": "TSLA 홀더들, ARK 매도에 가이던스 하향까지. 힘드시죠",
          "text": "$TSLA $361.83(-2.76%), 고점 -27%\n\nCathie Wood마저 줄였어요.\n가이던스도 175만→169만대로 내려갔어요.\n가장 믿었던 사람이 흔들리면 불안하죠.\n\n1/4",
          "thread": [
            "하지만 EV 시장 -28% 속 점유율 50%+.\n4월에 Cybercab, Roadster, 실적까지.\n\n회사의 체력 자체가 사라진 건 아니에요.\n가이던스가 조정된 거예요.\n\n2/4",
            "RSI 33이면 매도 압력도 극에 달한 거예요.\n여기서 더 빠지기보다 반등할 가능성도 있어요.\n\n3/4",
            "컨센서스 $407(+12.5%).\n4/21 실적을 기다려보세요.\n\n조급한 결정보다 확인이 먼저예요. Hold.\n\n4/4"
          ]
        }
      },
      "threads": {
        "fact": {
          "hook": "TSLA: 인도 가이던스 169만대 하향, ARK마저 줄였다",
          "text": "$TSLA $361.83(-2.76%), YTD -20%\n\n인도 가이던스 175만→169만대 하향. ARK까지 매도. 시위가 실제 숫자에 영향을 주기 시작했다.\n\n4월 Cybercab, Roadster, 4/21 실적. EV -28% 속 점유율 50%+는 건재하지만 가이던스 하향은 무겁다.\n\nRSI 33 과매도. Hold. 4/21 확인이 더 중요해졌다."
        },
        "witty": {
          "hook": "ARK마저 줄이면 누가 남아서 테슬라를 살까",
          "text": "$TSLA $361.83(-2.76%)\n\nCathie Wood가 줄였다. HSBC $119에 ARK 매도. 강세론자와 약세론자가 같은 날 같은 방향. 이건 보통 나쁜 신호다.\n\n가이던스 175만→169만대. 시위가 구호에서 숫자로 바뀌었다.\n\nEV -28% 속 점유율 50%+. 체력은 있는데 금이 갔다. 4월 카탈리스트가 답해줄 수 있을까.\n\nRSI 33. Hold가 Buy보다 현명한 순간."
        },
        "empathy": {
          "hook": "TSLA 주주 여러분, ARK 매도에 가이던스 하향까지 정말 힘드시죠",
          "text": "$TSLA $361.83(-2.76%), 고점 -27%\n\nCathie Wood마저 줄었다는 소식, 가이던스 169만대 하향까지. 가장 믿었던 사람이 흔들리면 불안한 게 당연해요.\n\n하지만 EV -28% 속 점유율 50%+를 지킨 건 테슬라뿐이에요. 4월에 카탈리스트가 집중돼 있어요.\n\nRSI 33. 매도 압력이 극에 달한 구간이에요. 4/21 실적을 기다려보세요.\n\nHold. 확인 후 움직여도 늦지 않아요."
        }
      }
    }
  }
}