[
  {
    "symbol": "TSLA",
    "name": "Tesla",
    "tag": "EV · Energy",
    "logo": "https://static2.finnhub.io/file/publicdatany/finnhubimage/stock_logo/TSLA.png",
    "addedAt": "2026-01-01"
  },
  {
    "symbol": "NVDA",
    "name": "NVIDIA",
    "tag": "AI · GPU",
    "logo": "https://static2.finnhub.io/file/publicdatany/finnhubimage/stock_logo/NVDA.png",
    "addedAt": "2026-01-01"
  },
  {
    "symbol": "BMNR",
    "name": "Bitmine",
    "tag": "ETH · Mining",
    "logo": "https://static2.finnhub.io/file/publicdatany/finnhubimage/stock_logo/950783675656.png",
    "addedAt": "2026-01-01"
  }
]