{
  "symbol": "SE",
  "companyName": "Sea Limited",
  "analysisDate": "2026-03-01",
  "currentPrice": 108.45,
  "marketCap": "$59.3B",
  "businessSummary": {
    "oneLiner": "Southeast Asia's largest e-commerce (Shopee), digital entertainment (Garena/Free Fire), and fintech (Monee) operator — Singapore-based global internet company",
    "description": "Sea Limited is a Singapore-based global tech company operating e-commerce (Shopee), gaming (Garena), and digital financial services (Monee) across Southeast Asia, Latin America, and Taiwan. TTM revenue $21.04B (+35.8% YoY), Q3 net income $375M (+145% YoY). Q4 2025 earnings due 3/3 — consensus EPS $0.62. Sustainable Growth Advisers opened a new position, and TIKR highlighted 'Net income jumped 145%, analysts see 75% upside'. Trading 45.6% below 52-week high.",
    "howTheyMakeMoney": [
      "Shopee: E-commerce commissions, advertising, logistics (SPX Express) — Q3 2025 revenue $3.8B (+36.6% YoY)",
      "Garena: Free Fire in-game sales, publishing — Q3 2025 revenue $653M (+31.2%), bookings $775M (+51%)",
      "Monee (fmr SeaMoney): Digital payments, lending, banking, insurance — Q3 2025 revenue $990M (+60.8%)",
      "Other product sales: $518M (+23.8% YoY)"
    ],
    "keyProducts": [
      "Shopee — #1 e-commerce in SE Asia & Latin America (2024 SE Asia GMV 52%)",
      "Garena Free Fire — Global mobile battle royale (bookings +51% YoY)",
      "Monee/ShopeePay — Digital payments & finance (loan portfolio $7.9B, +70%)",
      "SeaBank — Digital banking in Indonesia & Philippines",
      "SPX Express — Proprietary logistics network"
    ]
  },
  "keyMetrics": [
    {
      "name": "P/E (TTM)",
      "value": "47.36",
      "interpretation": "EPS $2.29. Reasonable for high-growth emerging tech"
    },
    {
      "name": "Forward P/E",
      "value": "25.40",
      "interpretation": "FY2026 EPS $4.27 expected. Attractive vs growth rate"
    },
    {
      "name": "Revenue Growth",
      "value": "+35.8% (TTM YoY)",
      "interpretation": "3 consecutive quarters of 30%+ growth. Q4 earnings 3/3"
    },
    {
      "name": "Operating Margin",
      "value": "8.2%",
      "interpretation": "Improving post-turnaround"
    },
    {
      "name": "FCF",
      "value": "$3.99B",
      "interpretation": "P/FCF 15x. Strong cash generation"
    },
    {
      "name": "Debt/Equity",
      "value": "0.41",
      "interpretation": "Manageable level. Net cash $5.66B"
    },
    {
      "name": "ROE",
      "value": "15.68%",
      "interpretation": "Improving profitability trend"
    },
    {
      "name": "PEG",
      "value": "0.40",
      "interpretation": "Significantly undervalued relative to growth"
    }
  ],
  "growthDrivers": [
    {
      "title": "Q4 Earnings 3/3 — Key Catalyst",
      "description": "Reporting pre-market 3/3. Consensus EPS $0.62. Shopee GMV growth and Monee profitability confirmation could trigger re-rating. 4th consecutive 30%+ growth expected."
    },
    {
      "title": "Sustainable Growth Advisers Opens New Position",
      "description": "SGA initiated a new SE position, focusing on the integrated e-commerce/payments/entertainment platform's long-term value."
    },
    {
      "title": "TIKR: 'Net Income +145%, Stock -46% From High'",
      "description": "Q3 revenue $6B (+38% YoY), net income $375M (+145%). 26 analysts average target $181.49. Extreme disconnect between fundamentals and price."
    },
    {
      "title": "Shopee SE Asia GMV 52% — Dominant #1 Expanding",
      "description": "2024 SE Asia GMV share 52% (up from 48%). Captured $12B of $14B total new GMV."
    }
  ],
  "competitiveAdvantage": {
    "summary": "Integrated SE Asia e-commerce, gaming, and fintech ecosystem is the core moat. Shopee/Monee/Garena cross-synergies and proprietary logistics (SPX Express) create barriers. GMV 52% vs #2 TikTok Shop (~18%).",
    "moats": [
      {
        "type": "Network Effects",
        "description": "Shopee's two-sided buyer-seller network with SPX Express logistics. 2024 SE Asia GMV 52%."
      },
      {
        "type": "Ecosystem Integration (Super App)",
        "description": "E-commerce→payments→finance→entertainment super app. Off-Shopee SPayLater +300%."
      },
      {
        "type": "Localization Advantage",
        "description": "Optimized for 11 SE Asian markets' languages, payments, logistics, regulations. Strong local edge vs Temu, Amazon."
      },
      {
        "type": "Data Moat",
        "description": "Integrated e-commerce/payments/lending/gaming data for AI personalization. Enhanced by Google AI partnership."
      }
    ],
    "competitors": [
      {
        "name": "TikTok Shop",
        "detail": "SE Asia e-commerce #2, GMV ~18%. Strong in live commerce."
      },
      {
        "name": "Lazada (Alibaba)",
        "detail": "Fallen to #3 in SE Asia. Overtaken by TikTok Shop."
      },
      {
        "name": "Temu (PDD Holdings)",
        "detail": "Ultra-low-cost cross-border. Expanding in SE Asia and Brazil. MAU +55%."
      },
      {
        "name": "MercadoLibre",
        "detail": "Latin America #1. Direct competition with Shopee in Brazil."
      },
      {
        "name": "Grab Holdings",
        "detail": "SE Asia super app. Indirect fintech competition with Monee."
      }
    ]
  },
  "recentNews": [
    {
      "date": "2026-02-28",
      "headline": "Sustainable Growth Advisers Opens New SE Position",
      "significance": "Focused on integrated platform strategy and margin improvement potential. Institutional inflow signal.",
      "url": "https://ca.finance.yahoo.com/news/sustainable-growth-advisers-backs-sea-221151325.html"
    },
    {
      "date": "2026-02-28",
      "headline": "TIKR: 'Net Income +145%, Analysts See 75% Upside'",
      "significance": "Q3 revenue $6B (+38%), net income +145%. 26 analysts target $181.49. 46% below 52-week high.",
      "url": "https://www.tikr.com/blog/sea-limiteds-net-income-jumped-145-analysts-see-75-upside"
    },
    {
      "date": "2026-02-27",
      "headline": "Q4 Earnings Preview — Consensus EPS $0.62, Due 3/3",
      "significance": "TradingView earnings preview. Shopee momentum vs credit cost concerns.",
      "url": "https://www.tradingview.com/news/reuters.com,2026:newsml_L8N3ZN1JF:0-sea-ltd-expected-to-post-earnings-of-62-cents-a-share-earnings-preview/"
    },
    {
      "date": "2026-02-27",
      "headline": "Insider Monkey: 'What Makes Sea Limited an Investment Bet'",
      "significance": "Highlights Shopee GMV 52%, Monee fintech growth, PEG 0.40 undervaluation.",
      "url": "https://www.insidermonkey.com/blog/what-makes-sea-limited-se-an-investment-bet-1694270/"
    },
    {
      "date": "2026-02-27",
      "headline": "SE -2.2% — Inflation Surprise Hits Emerging Growth",
      "significance": "PPI beat expectations. Negative for emerging market growth stocks. Wait-and-see ahead of earnings.",
      "url": "https://www.cnbc.com/2026/02/26/stock-market-today-live-updates.html"
    }
  ],
  "analystOpinions": {
    "consensusTarget": 181.49,
    "highTarget": 250,
    "lowTarget": 130,
    "upsidePercent": 67.35,
    "buyCount": 26,
    "holdCount": 0,
    "sellCount": 0,
    "notableComment": "26 analysts unanimous Buy/Strong Buy. TIKR consensus $181.49 (+67%). SGA new position. Q4 earnings beat could trigger re-rating."
  },
  "risks": [
    {
      "severity": "high",
      "title": "Q4 Earnings Uncertainty — Credit Costs and FX Headwinds",
      "description": "3/3 earnings. Rising credit costs, higher OpEx, SE Asian currency weakness."
    },
    {
      "severity": "medium",
      "title": "46% Below 52-Week High",
      "description": "$199→$108. Below both 50-day and 200-day SMAs. Technical downtrend."
    },
    {
      "severity": "medium",
      "title": "Inflation Surprise — Emerging Growth Weakness",
      "description": "PPI beat pushing back rate cut expectations. Negative for emerging market growth."
    },
    {
      "severity": "medium",
      "title": "Temu and TikTok Shop Competition Intensifying",
      "description": "SE Asian e-commerce competition heating up. Potential Shopee margin pressure."
    },
    {
      "severity": "low",
      "title": "Gaming Revenue Share Declining",
      "description": "Garena's revenue contribution shrinking. Free Fire sustainability uncertain."
    }
  ],
  "buyReasons": [
    {
      "title": "PEG 0.40 — Extreme Undervaluation vs Growth",
      "rationale": "35%+ growth at P/E 47. TIKR: '75% upside'. Rare valuation among growth stocks."
    },
    {
      "title": "Q4 Earnings Catalyst (3/3) + SGA New Position",
      "rationale": "Institutional inflows + earnings surprise potential. Re-rating catalysts concentrated."
    },
    {
      "title": "26 Analysts Unanimous Buy — Consensus +67%",
      "rationale": "Target $181.49. Maximum upside potential among coverage."
    },
    {
      "title": "Net Cash $5.66B + P/FCF 15x",
      "rationale": "SE Asia's largest e-commerce cash generation. Ample valuation safety margin."
    }
  ],
  "technicalPosition": {
    "week52High": 199.3,
    "week52Low": 99.5,
    "currentPositionPercent": 8.97,
    "sma50": 120.0,
    "sma50Signal": "below",
    "sma200": 140.0,
    "sma200Signal": "below",
    "rsi": 42.0,
    "rsiSignal": "neutral"
  },
  "overallOpinion": [
    "Sea Limited closed at $108.45, trading 46% below its 52-week high. Q4 earnings on 3/3 is the make-or-break catalyst.",
    "PEG 0.40 and P/FCF 15x represent extreme undervaluation for a 35%+ growth company. 26 unanimous Buy ratings and SGA's new position signal institutional confidence.",
    "The key is 3/3 Q4 earnings. Beat on consensus EPS $0.62 could trigger re-rating. However, credit cost increases and FX headwinds are near-term downside risks."
  ],
  "sources": [
    {
      "name": "Yahoo Finance",
      "url": "https://ca.finance.yahoo.com/news/sustainable-growth-advisers-backs-sea-221151325.html",
      "description": "SGA new position opening"
    },
    {
      "name": "TIKR",
      "url": "https://www.tikr.com/blog/sea-limiteds-net-income-jumped-145-analysts-see-75-upside",
      "description": "Net income 145% surge, 75% upside analysis"
    },
    {
      "name": "TradingView",
      "url": "https://www.tradingview.com/news/reuters.com,2026:newsml_L8N3ZN1JF:0-sea-ltd-expected-to-post-earnings-of-62-cents-a-share-earnings-preview/",
      "description": "Q4 earnings preview"
    },
    {
      "name": "Insider Monkey",
      "url": "https://www.insidermonkey.com/blog/what-makes-sea-limited-se-an-investment-bet-1694270/",
      "description": "Investment case analysis"
    },
    {
      "name": "CNBC",
      "url": "https://www.cnbc.com/2026/02/26/stock-market-today-live-updates.html",
      "description": "Market news"
    },
    {
      "name": "Yahoo Finance",
      "url": "https://finance.yahoo.com/news/makes-sea-limited-se-investment-143418379.html",
      "description": "SE investment analysis"
    },
    {
      "name": "Angel One",
      "url": "https://www.angelone.in/us-stocks/sea-limited",
      "description": "Real-time price"
    },
    {
      "name": "MarketBeat",
      "url": "https://www.marketbeat.com/stocks/NYSE/SE/",
      "description": "Analyst data"
    }
  ],
  "snsContent": {
    "threads": {
      "hook": "Net income up 145% but stock down 46%? Something's off 🧐",
      "text": "Sea Limited at $108, nearly half off its 52-week high.\n\n26 analysts ALL say Buy, target $181 (+67%).\n\nQ4 earnings 3/3 could be the turning point.\n\nPEG 0.40... is this price for real?\n\n👉 investory.kro.kr/stock/SE/analysis/2026-03-01"
    },
    "telegram": {
      "hook": "🌏 SE $108 — Q4 Earnings D-2, 26 Analysts Unanimous Buy",
      "text": "📊 Sea Limited Daily Analysis (3/1)\n\nPrice: $108.45 (-2.2%)\nMkt Cap: $59.3B | P/E: 47x | Fwd P/E: 25x\n\n🔥 Key Points:\n• Q4 earnings 3/3 — consensus EPS $0.62\n• SGA opens new investment position\n• TIKR: Net income +145%, analysts see 75% upside\n• PEG 0.40 — cheapest growth stock valuation\n• Shopee SE Asia GMV 52%\n\n📈 Analysts: Buy 26 unanimous, target $181 (+67%)\n\n⚠️ Risks: Q4 credit costs, FX headwinds\n✅ Opportunity: Extreme undervaluation + earnings catalyst D-2\n\nFull analysis 👉 investory.kro.kr/stock/SE/analysis/2026-03-01"
    }
  }
}